TensorART/__init__.py
TensorART/main.py
TensorART-1.0.0.dist-info/METADATA
TensorART-1.0.0.dist-info/WHEEL
TensorART-1.0.0.dist-info/top_level.txt
TensorART-1.0.0.dist-info/RECORD
