Metadata-Version: 2.1
Name: TensorART
Version: 1.0.0
Summary: API BASED IMAGE GENERATOR PYPI.
Home-page: https://github.com/XZeipher/TensorAI
Author: Alpha Coder
Author-email: alphacoders@yahoo.com
License: GNU General Public License v3.0
Keywords: ai,ml,bot,api,image,prompt
Classifier: Framework :: AsyncIO
Classifier: Development Status :: 3 - Alpha
Classifier: Intended Audience :: Developers
Classifier: License :: OSI Approved :: GNU General Public License v2 or later (GPLv2+)
Classifier: Natural Language :: English
Classifier: Operating System :: OS Independent
Classifier: Programming Language :: Python :: 3.7
Classifier: Programming Language :: Python :: 3.8
Classifier: Programming Language :: Python :: 3.9
Classifier: Programming Language :: Python :: 3.10
Classifier: Topic :: Internet :: WWW/HTTP
Classifier: Topic :: Software Development :: Libraries
Classifier: Topic :: Software Development :: Build Tools
Requires-Dist: aiohttp
Requires-Dist: aiofiles
